[{"name":"sql.active_record","payload":{"sql":"            SELECT a.attname, format_type(a.atttypid, a.atttypmod),\n                     pg_get_expr(d.adbin, d.adrelid), a.attnotnull, a.atttypid, a.atttypmod\n              FROM pg_attribute a LEFT JOIN pg_attrdef d\n                ON a.attrelid = d.adrelid AND a.attnum = d.adnum\n             WHERE a.attrelid = '\"users\"'::regclass\n               AND a.attnum > 0 AND NOT a.attisdropped\n             ORDER BY a.attnum\n","name":"SCHEMA","connection_id":70219197434140,"binds":[]},"time":"2013-11-13T18:49:02-05:00","transaction_id":"c7ab56be35f2bca5bf0e","end":"2013-11-13T18:49:02-05:00","duration":1.2229999999999999},{"name":"sql.active_record","payload":{"sql":"            SELECT COUNT(*)\n            FROM pg_class c\n            LEFT JOIN pg_namespace n ON n.oid = c.relnamespace\n            WHERE c.relkind in ('v','r')\n            AND c.relname = 'users'\n            AND n.nspname = ANY (current_schemas(false))\n","name":"SCHEMA","connection_id":70219197434140,"binds":[]},"time":"2013-11-13T18:49:02-05:00","transaction_id":"c7ab56be35f2bca5bf0e","end":"2013-11-13T18:49:02-05:00","duration":0.777},{"name":"sql.active_record","payload":{"sql":"          SELECT attr.attname\n          FROM pg_attribute attr\n          INNER JOIN pg_constraint cons ON attr.attrelid = cons.conrelid AND attr.attnum = cons.conkey[1]\n          WHERE cons.contype = 'p'\n            AND cons.conrelid = '\"users\"'::regclass\n","name":"SCHEMA","connection_id":70219197434140,"binds":[]},"time":"2013-11-13T18:49:02-05:00","transaction_id":"c7ab56be35f2bca5bf0e","end":"2013-11-13T18:49:02-05:00","duration":0.6890000000000001},{"name":"sql.active_record","payload":{"sql":"SELECT  \"users\".* FROM \"users\"  WHERE \"users\".\"id\" = $1 LIMIT 1","name":"User Load","connection_id":70219197434140,"binds":[[{"name":"id","sql_type":"integer","null":false,"limit":null,"precision":null,"scale":null,"type":"integer","default":null,"primary":true,"coder":null},4]]},"time":"2013-11-13T18:49:02-05:00","transaction_id":"c7ab56be35f2bca5bf0e","end":"2013-11-13T18:49:02-05:00","duration":0.32},{"name":"sql.active_record","payload":{"sql":"SELECT  \"cases\".* FROM \"cases\"  WHERE \"cases\".\"id\" = $1 LIMIT 1","name":"Case Load","connection_id":70219197434140,"binds":[[{"name":"id","sql_type":"integer","null":false,"limit":null,"precision":null,"scale":null,"type":"integer","default":null,"primary":true,"coder":null},"3"]]},"time":"2013-11-13T18:49:02-05:00","transaction_id":"c7ab56be35f2bca5bf0e","end":"2013-11-13T18:49:02-05:00","duration":0.432},{"name":"sql.active_record","payload":{"sql":"SELECT  \"users\".* FROM \"users\"  WHERE \"users\".\"id\" = 2 LIMIT 1","name":"User Load","connection_id":70219197434140,"binds":[]},"time":"2013-11-13T18:49:02-05:00","transaction_id":"c7ab56be35f2bca5bf0e","end":"2013-11-13T18:49:02-05:00","duration":1.167},{"name":"process_action.action_controller","payload":{"controller":"CasesController","action":"edit","params":{"action":"edit","controller":"cases","id":"3"},"format":"html","method":"GET","path":"/cases/3/edit","status":302,"view_runtime":null,"db_runtime":4.608},"time":"2013-11-13T18:49:02-05:00","transaction_id":"aecc25fd133ca129e06e","end":"2013-11-13T18:49:02-05:00","duration":54.699999999999996}]