[{"name":"render_template.action_view","payload":{"identifier":"/Users/ML/courtPO/app/views/welcome/home.html.erb","layout":"layouts/application"},"time":"2013-11-13T16:41:48-05:00","transaction_id":"245950b643bc9dc4783c","end":"2013-11-13T16:41:48-05:00","duration":5.801},{"name":"sql.active_record","payload":{"sql":"            SELECT a.attname, format_type(a.atttypid, a.atttypmod),\n                     pg_get_expr(d.adbin, d.adrelid), a.attnotnull, a.atttypid, a.atttypmod\n              FROM pg_attribute a LEFT JOIN pg_attrdef d\n                ON a.attrelid = d.adrelid AND a.attnum = d.adnum\n             WHERE a.attrelid = '\"users\"'::regclass\n               AND a.attnum > 0 AND NOT a.attisdropped\n             ORDER BY a.attnum\n","name":"SCHEMA","connection_id":70251536379060,"binds":[]},"time":"2013-11-13T16:41:49-05:00","transaction_id":"245950b643bc9dc4783c","end":"2013-11-13T16:41:49-05:00","duration":10.647},{"name":"sql.active_record","payload":{"sql":"            SELECT COUNT(*)\n            FROM pg_class c\n            LEFT JOIN pg_namespace n ON n.oid = c.relnamespace\n            WHERE c.relkind in ('v','r')\n            AND c.relname = 'users'\n            AND n.nspname = ANY (current_schemas(false))\n","name":"SCHEMA","connection_id":70251536379060,"binds":[]},"time":"2013-11-13T16:41:49-05:00","transaction_id":"245950b643bc9dc4783c","end":"2013-11-13T16:41:49-05:00","duration":3.113},{"name":"sql.active_record","payload":{"sql":"          SELECT attr.attname\n          FROM pg_attribute attr\n          INNER JOIN pg_constraint cons ON attr.attrelid = cons.conrelid AND attr.attnum = cons.conkey[1]\n          WHERE cons.contype = 'p'\n            AND cons.conrelid = '\"users\"'::regclass\n","name":"SCHEMA","connection_id":70251536379060,"binds":[]},"time":"2013-11-13T16:41:49-05:00","transaction_id":"245950b643bc9dc4783c","end":"2013-11-13T16:41:49-05:00","duration":2.028},{"name":"sql.active_record","payload":{"sql":"SHOW search_path","name":"SCHEMA","connection_id":70251536379060,"binds":[]},"time":"2013-11-13T16:41:49-05:00","transaction_id":"245950b643bc9dc4783c","end":"2013-11-13T16:41:49-05:00","duration":0.357},{"name":"sql.active_record","payload":{"sql":"SELECT  \"users\".* FROM \"users\"  WHERE \"users\".\"id\" = $1 LIMIT 1","name":"User Load","connection_id":70251536379060,"binds":[[{"name":"id","sql_type":"integer","null":false,"limit":null,"precision":null,"scale":null,"type":"integer","default":null,"primary":true,"coder":null},4]]},"time":"2013-11-13T16:41:49-05:00","transaction_id":"245950b643bc9dc4783c","end":"2013-11-13T16:41:49-05:00","duration":9.732},{"name":"render_partial.action_view","payload":{"identifier":"/Users/ML/courtPO/app/views/layouts/_nav.html.erb"},"time":"2013-11-13T16:41:49-05:00","transaction_id":"245950b643bc9dc4783c","end":"2013-11-13T16:41:49-05:00","duration":159.079},{"name":"process_action.action_controller","payload":{"controller":"WelcomeController","action":"home","params":{"controller":"welcome","action":"home"},"format":"html","method":"GET","path":"/","status":200,"view_runtime":244.034,"db_runtime":25.877},"time":"2013-11-13T16:41:48-05:00","transaction_id":"245950b643bc9dc4783c","end":"2013-11-13T16:41:49-05:00","duration":270.849}]